[
	{
		"id": 1,
		"title": "Compu",
		"description": "Nuevita",
		"code": "has87",
		"price": 2500,
		"status": true,
		"stock": 2,
		"category": "PC",
		"thumbnail": []
	},
	{
		"id": 2,
		"title": "Play 4",
		"description": "Usada",
		"code": "has7",
		"price": 600,
		"status": true,
		"stock": 20,
		"category": "Consolas",
		"thumbnail": []
	},
	{
		"id": 3,
		"title": "Play 3",
		"description": "Usada",
		"code": "has71",
		"price": 200,
		"status": true,
		"stock": 20,
		"category": "Consolas",
		"thumbnail": []
	},
	{
		"id": 4,
		"title": "Play 5",
		"description": "Nueva",
		"code": "has711235",
		"price": 1800,
		"status": true,
		"stock": 20,
		"category": "Consolas",
		"thumbnail": []
	},
	{
		"id": 5,
		"title": "Notebook DELL",
		"description": "Nueva",
		"code": "has7asdas",
		"price": 1200,
		"status": true,
		"stock": 20,
		"category": "Notebook",
		"thumbnail": []
	},
	{
		"id": "926a3ec2-6afc-4a15-934c-a47339af97e4",
		"title": "Joystick XBOX",
		"description": "nuevo",
		"price": "175",
		"thumbnail": [],
		"code": "1239asdaasda",
		"stock": "20"
	},
	{
		"id": "68ad8e8a-51a2-4d1d-bad9-0572c2cfdd27",
		"title": "Joystick XBOX 2",
		"description": "nuevo2",
		"price": "175",
		"thumbnail": [],
		"code": "13saasdas",
		"stock": "20"
	}
]